mflow/__init__.py
mflow/mflow.py
mflow/utils.py
mflow/cli/__init__.py
mflow/cli/dump.py
mflow/cli/generate.py
mflow/cli/replay.py
mflow/cli/split.py
mflow/cli/stats.py
mflow/handlers/__init__.py
mflow/handlers/array_1_0.py
mflow/handlers/dheader_1_0.py
mflow/handlers/dimage_1_0.py
mflow/handlers/dseries_end_1_0.py
mflow/handlers/raw_1_0.py
psi_mflow-1.0.0.dist-info/LICENSE
psi_mflow-1.0.0.dist-info/METADATA
psi_mflow-1.0.0.dist-info/WHEEL
psi_mflow-1.0.0.dist-info/top_level.txt
psi_mflow-1.0.0.dist-info/RECORD
