Metadata-Version: 2.1
Name: psi-mflow
Version: 1.0.0
Summary: Utility library for ZMQ data streaming
Home-page: https://github.com/paulscherrerinstitute/mflow
Author: Paul Scherrer Institute
License: GNU GPLv3
License-File: LICENSE
Requires-Dist: numpy
Requires-Dist: pyzmq
